{
  "date": "2026-01-03",
  "scraped_at": "2026-02-28T10:36:23Z",
  "unit": "PLN/MWh",
  "prices": [
    {
      "time": "2026-01-03 00:00:00+01:00",
      "price": 275.0
    },
    {
      "time": "2026-01-03 01:00:00+01:00",
      "price": 259.8
    },
    {
      "time": "2026-01-03 02:00:00+01:00",
      "price": 236.0
    },
    {
      "time": "2026-01-03 03:00:00+01:00",
      "price": 220.7
    },
    {
      "time": "2026-01-03 04:00:00+01:00",
      "price": 230.88
    },
    {
      "time": "2026-01-03 05:00:00+01:00",
      "price": 236.36
    },
    {
      "time": "2026-01-03 06:00:00+01:00",
      "price": 267.99
    },
    {
      "time": "2026-01-03 07:00:00+01:00",
      "price": 325.0
    },
    {
      "time": "2026-01-03 08:00:00+01:00",
      "price": 363.0
    },
    {
      "time": "2026-01-03 09:00:00+01:00",
      "price": 377.76
    },
    {
      "time": "2026-01-03 10:00:00+01:00",
      "price": 367.64
    },
    {
      "time": "2026-01-03 11:00:00+01:00",
      "price": 363.0
    },
    {
      "time": "2026-01-03 12:00:00+01:00",
      "price": 356.59
    },
    {
      "time": "2026-01-03 13:00:00+01:00",
      "price": 381.99
    },
    {
      "time": "2026-01-03 14:00:00+01:00",
      "price": 421.99
    },
    {
      "time": "2026-01-03 15:00:00+01:00",
      "price": 497.0
    },
    {
      "time": "2026-01-03 16:00:00+01:00",
      "price": 499.5
    },
    {
      "time": "2026-01-03 17:00:00+01:00",
      "price": 509.0
    },
    {
      "time": "2026-01-03 18:00:00+01:00",
      "price": 500.0
    },
    {
      "time": "2026-01-03 19:00:00+01:00",
      "price": 497.0
    },
    {
      "time": "2026-01-03 20:00:00+01:00",
      "price": 463.99
    },
    {
      "time": "2026-01-03 21:00:00+01:00",
      "price": 454.9
    },
    {
      "time": "2026-01-03 22:00:00+01:00",
      "price": 420.0
    },
    {
      "time": "2026-01-03 23:00:00+01:00",
      "price": 366.24
    }
  ]
}